quickhtml/__init__.py
quickhtml/__main__.py
quickhtml/quickhtml.py
quickhtml-2.0.17.dist-info/LICENSE
quickhtml-2.0.17.dist-info/METADATA
quickhtml-2.0.17.dist-info/WHEEL
quickhtml-2.0.17.dist-info/top_level.txt
quickhtml-2.0.17.dist-info/RECORD
