Metadata-Version: 2.1
Name: quickhtml
Version: 2.0.17
Summary: A simple Markdown to HTML preprocessor that doesn't require third-party modules.
Home-page: https://github.com/ckc-dev/QuickHTML
Author: ckc-dev
Author-email: ckc-dev@pm.me
License: UNKNOWN
Platform: UNKNOWN
Classifier: Programming Language :: Python :: 3
Classifier: License :: OSI Approved :: GNU General Public License v3 (GPLv3)
Classifier: Operating System :: OS Independent
Requires-Python: >=3.6
License-File: LICENSE
